tpa_map_interface/MapInterface.py
tpa_map_interface/__init__.py
tpa_map_interface/import_veh_dyn_info.py
tpa_map_interface-0.4.dist-info/LICENSE
tpa_map_interface-0.4.dist-info/METADATA
tpa_map_interface-0.4.dist-info/WHEEL
tpa_map_interface-0.4.dist-info/top_level.txt
tpa_map_interface-0.4.dist-info/RECORD
